aryabhatta/__init__.py
aryabhatta/area.py
aryabhatta/currency.py
aryabhatta/data.py
aryabhatta/datarate.py
aryabhatta/energy.py
aryabhatta/force.py
aryabhatta/frequency.py
aryabhatta/length.py
aryabhatta/mass.py
aryabhatta/moles.py
aryabhatta/power.py
aryabhatta/pressure.py
aryabhatta/speed.py
aryabhatta/temp.py
aryabhatta/time.py
aryabhatta/torque.py
aryabhatta/volume.py
aryabhatta_units-0.1.1.dist-info/licenses/LICENSE
aryabhatta_units-0.1.1.dist-info/METADATA
aryabhatta_units-0.1.1.dist-info/WHEEL
aryabhatta_units-0.1.1.dist-info/top_level.txt
aryabhatta_units-0.1.1.dist-info/RECORD
