Metadata-Version: 2.4
Name: aryabhatta-units
Version: 0.1.1
Summary: A comprehensive unit conversion library inspired by Aryabhata
Author: Prateek Kumar Rai
License: MIT License
Classifier: Programming Language :: Python :: 3
Classifier: License :: OSI Approved :: MIT License
Classifier: Operating System :: OS Independent
Requires-Python: >=3
License-File: LICENSE
Requires-Dist: requests>=2.01
Dynamic: license-file
